README
setup.py
dear/__init__.py
dear/crop.py
dear/spectrogram.py
dear.egg-info/PKG-INFO
dear.egg-info/SOURCES.txt
dear.egg-info/dependency_links.txt
dear.egg-info/top_level.txt
dear/analysis/__init__.py
dear/analysis/mfcc.py
dear/io/__init__.py
dear/io/_dc_audioread.py
dear/io/_decoder.py
dear/io/_io_base.py
dear/spectrum/__init__.py
dear/spectrum/_base.py
dear/spectrum/auditory.py
dear/spectrum/cqt.py
dear/spectrum/dft.py