Metadata-Version: 1.0
Name: dear
Version: 0.1
Summary: Dear EARs Audio Analysis Framework
Home-page: http://dongying.github.com/dear
Author: Dongying Zhang
Author-email: zhdongying@gmail.com
License: MIT LICENSE
Platform: UNKNOWN
